{"header": {"vol": "166", "num": "24", "wkday": "Wednesday", "month": "February", "day": "5", "year": "2020", "chamber": "House", "pages": "H845-H847", "extension": false}, "content": [{"kind": "Unknown", "speaker": "Unknown", "text": "   Under clause 2 of rule XIV, executive communications were taken from \nthe Speaker's table and referred as follows:\n\n       3710. A letter from the Senior Legal Advisor for Regulatory \n     Affairs, Department of the Treasury, Financial Stability \n     Oversight Council, transmitting the Council's final \n     interpretive guidance -- Authority To Require Supervision and \n     Regulation of Certain Nonbank Financial Companies (RIN: 4030-\n     ZA00) received February 3, 2020, pursuant to 5 U.S.C. \n     801(a)(1)(A); Public Law 104-121, Sec. 251; (110 Stat. 868); \n     to the Committee on Financial Services.\n       3711. A letter from the Director, Regulatory Management \n     Division, Environmental Protection Agency, transmitting the \n     Agency's final rule -- Flutriafol; Pesticide Tolerances [EPA-\n     HQ-OPP-2018-0297; FRL-10004-03] received February 3, 2019, \n     pursuant to 5 U.S.C. 801(a)(1)(A); Public Law 104-121, Sec.\n\n\n     251; (110 Stat. 868); to the Committee on Energy and \n     Commerce.\n       3712. A letter from the Director, Regulatory Management \n     Agency, Environmental Protection Agency, transmitting the \n     Agency's final rule -- Prohexadione Calcium; Pesticide \n     Tolerances [EPA-HQ-OPP-2018-0785; FRL-10003-04] received \n     February 3, 2020, pursuant to 5 U.S.C. 801(a)(1)(A); Public \n     Law 104-121, Sec. 251; (110 Stat. 868); to the Committee on \n     Energy and Commerce.\n       3713. A letter from the Director, Regulatory Management \n     Division, Environmental Protection Agency, transmitting the \n     Agency's final rule -- Propanamide, 2-hydroxy-N, N-dimethyl-; \n     Exemption from the Requirement of a Tolerance [EPA-HQ-OPP-\n     2019-0279; FRL-10003-07] received February 3, 2020, pursuant \n     to 5 U.S.C. 801(a)(1)(A); Public Law 104-121, Sec. 251; (110 \n     Stat. 868); to the Committee on Energy and Commerce.\n       3714. A letter from the Director, Regulatory Management \n     Division, Environmental Protection Agency, transmitting the \n     Agency's final rule -- Cyantraniliprole; Pesticide Tolerances \n     [EPA-HQ-OPP-2017-0694; FRL-10004-23] received February 3, \n     2020, pursuant to 5 U.S.C. 801(a)(1)(A); Public Law 104-121, \n     Sec. 251; (110 Stat. 868); to the Committee on Energy and \n     Commerce.\n       3715. A letter from the Director, Regulatory Management \n     Division, Environmental Protection Agency, transmitting the \n     Agency's final rule -- Difenoconazole; Pesticide Tolerances \n     [EPA-HQ-OPP-2018-0178 and EPA-HQ-OPP-2019-0076; FRL-10002-06] \n     received February 3, 2020, pursuant to 5 U.S.C. 801(a)(1)(A); \n     Public Law 104-121, Sec. 251; (110 Stat. 868); to the \n     Committee on Energy and Commerce.\n       3716. A letter from the Director, Regulatory Management \n     Division, Environmental Protection Agency, transmitting the \n     Agency's final rule -- Environmental Protection Agency \n     Acquisition Regulation (EPAAR) Clause Update for Submission \n     of Invoices [EPA-HQ-OMS-2018-0742; FRL-10002-43-OMS] received \n     February 3, 2020, pursuant to 5 U.S.C. 801(a)(1)(A); Public \n     Law 104-121, Sec. 251; (110 Stat. 868); to the Committee on \n     Energy and Commerce.\n       3717. A letter from the Director, Regulatory Management \n     Division, Environmental Protection Agency, transmitting the \n     Agency's final rule -- Ethylenebis(oxyethylene) bis[3-(5-\n     tert-butyl-4-hydroxy-m-tolyl) propionate]; Exemption from the \n     Requirement of a Tolerance [EPA-HQ-OPP-2019-01296; FRL-10002-\n     96] received February 3, 2020, pursuant to 5 U.S.C. \n     801(a)(1)(A); Public Law 104-121, Sec. 251; (110 Stat. 868); \n     to the Committee on Energy and Commerce.\n       3718. A letter from the Director, Regulatory Management \n     Division, Environmental Protection Agency, transmitting the \n     Agency's final rule -- Air Plan Approval; Texas; Revisions to \n     Control of Air Pollution by Permits for New Construction or \n     Modification [EPA-R06-OAR-2019-0043; FRL-10004-67-Region 6] \n     received February 3, 2020, pursuant to 5 U.S.C. 801(a)(1)(A); \n     Public Law 104-121, Sec. 251; (110 Stat. 868); to the \n     Committee on Energy and Commerce.\n       3719. A letter from the Director, Regulatory Management \n     Division, Environmental Protection Agency, transmitting the \n     Agency's final rule -- Approval and Promulgation of Air \n     Quality Implementation Plans; District of Columbia; \n     Reasonably Available Control Technology State Implementation \n     Plan for Nitrogen Oxides Under the 2008 Ozone National \n     Ambient Air Quality Standard [EPA-R03-OAR-2019-0207; FRL-\n     10004-84-Region 3] received February 3, 2020, pursuant to 5 \n     U.S.C. 801(a)(1)(A); Public Law 104-121, Sec. 251; (110 Stat. \n     868); to the Committee on Energy and Commerce.\n       3720. A letter from the Director, Regulatory Management \n     Division, Environmental Protection Agency, transmitting the \n     Agency's final rule -- Chlorfenapyr; Pesticide Tolerances \n     [EPA-HQ-OPP-2018-0783; FRL-10002-05] received February 3, \n     2020, pursuant to 5 U.S.C. 801(a)(1)(A); Public Law 104-121, \n     Sec. 251; (110 Stat. 868); to the Committee on Energy and \n     Commerce.\n       3721. A letter from the Director, Regulatory Management \n     Division, Environmental Protection Agency, transmitting the \n     Agency's final rule -- Air Plan Approval; Texas; Houston-\n     Galveston-Brazoria Area Redesignation and Maintenance Plan \n     for Revoked Ozone National Ambient Air Quality Standards; \n     Section 185 Fee Program [EPA-R06-OAR-2018-0715; FRL-10002-70-\n     Region 6] received February 3, 2020, pursuant to 5 U.S.C. \n     801(a)(1)(A); Public Law 104-121, Sec. 251; (110 Stat. 868); \n     to the Committee on Energy and Commerce.\n       3722. A letter from the Director, Regulatory Management \n     Division, Environmental Protection Agency, transmitting the \n     Agency's final rule -- Air Plan Approval; Ohio; Prevention of \n     Significant Deterioration Greenhouse Gas Tailoring Rule [EPA-\n     R05-OAR-2012-0990; FRL-10005-04-Region 5] received February \n     3, 2020, pursuant to 5 U.S.C. 801(a)(1)(A); Public Law 104-\n     121, Sec. 251; (110 Stat. 868); to the Committee on Energy \n     and Commerce.\n       3723. A letter from the Director, Regulatory Management \n     Division, Environmental Protection Agency, transmitting the \n     Agency's final rule -- Air Plan Approval; Connecticut; \n     Transport State Implementation Plan for the 2008 Ozone \n     Standard [EPA-R01-OAR-2019-0513; FRL-10004-95-Region 1] \n     received February 3, 2020, pursuant to 5 U.S.C. 801(a)(1)(A); \n     Public Law 104-121, Sec. 251; (110 Stat. 868); to the \n     Committee on Energy and Commerce.\n       3724. A letter from the Director, Regulatory Management \n     Division, Environmental Protection Agency, transmitting the \n     Agency's final rule -- Acetamiprid; Pesticide Tolerances \n     [EPA-HQ-OPP-2018-0784; FRL-10004-12] received February 3, \n     2020, pursuant to 5 U.S.C. 801(a)(1)(A); Public Law 104-121, \n     Sec. 251; (110 Stat. 868); to the Committee on Energy and \n     Commerce.\n       3725. A letter from the Associate Director of International \n     Economics, Bureau of Economic Analysis, Department of \n     Commerce, transmitting the Department's final rule -- Direct \n     Investment Surveys: BE-10, Benchmark Survey of U.S. Direct \n     Investment Abroad [Docket No.: 191104-0074] (RIN: 0691-AA89) \n     received February 3, 2019, pursuant to 5 U.S.C. 801(a)(1)(A); \n     Public Law 104-121, Sec. 251; (110 Stat. 868); to the \n     Committee on Foreign Affairs.\n       3726. A letter from the Chairman, Council of the District \n     of Columbia, transmitting D.C. Act 23-204, ``Primary Election \n     Filing Requirement Temporary Amendment Act of 2020'', \n     pursuant to Public Law 93-198, Sec. 602(c)(1); (87 Stat. \n     814); to the Committee on Oversight and Reform.\n       3727. A letter from the Chairman, Council of the District \n     of Columbia, transmitting D.C. Act 23-216, ``Parkside Parcel \n     E and J Mixed-Income Apartments Tax Abatement Temporary \n     Amendment Act of 2020'', pursuant to Public Law 93-198, Sec. \n     602(c)(1); (87 Stat. 814); to the Committee on Oversight and \n     Reform.\n       3728. A letter from the Chairman, Council of the District \n     of Columbia, transmitting D.C. Act 23-203, ``Fiscal Year 2020 \n     Budget Support Clarification Amendment Act of 2019'', \n     pursuant to Public Law 93-198, Sec. 602(c)(1); (87 Stat. \n     814); to the Committee on Oversight and Reform.\n       3729. A letter from the Senior Advisor, Office of Inspector \n     General, Department of Health and Human Services, \n     transmitting a notification of a discontinuation of service \n     in acting role, pursuant to 5 U.S.C. 3349(a); Public Law 105-\n     277, 151(b); (112 Stat. 2681-614); to the Committee on \n     Oversight and Reform.\n       3730. A letter from the White House Liaison, Office of \n     Legislation and Congressional Affairs, Department of \n     Education, transmitting a notification of a designation of \n     acting officer and a discontinuation of service in acting \n     role, pursuant to 5 U.S.C. 3349(a); Public Law 105-277, \n     151(b); (112 Stat. 2681-614); to the Committee on Oversight \n     and Reform.\n       3731. A letter from the Assistant Attorney General, Office \n     of Legislative Affairs, Department of Justice, transmitting \n     the Uniformed and Overseas Citizens Absentee Voting Act \n     Annual Report to Congress 2019, pursuant to 52 U.S.C. \n     20307(b); Public Law 99-410, Sec. 105(b) (as amended by \n     Public Law 111-84, Sec. 587(2)); (123 Stat. 2333); to the \n     Committee on House Administration.\n       3732. A letter from the Secretary, Federal Maritime \n     Commission, transmitting the Commission's final rule -- \n     Inflation Adjustment of Civil Monetary Penalties [Docket No.: \n     20-01] (RIN: 3072-AC79) received February 3, 2020, pursuant \n     to 5 U.S.C. 801(a)(1)(A); Public Law 104-121, Sec. 251; (110 \n     Stat. 868); to the Committee on the Judiciary.\n       3733. A letter from the Acting General Counsel, National \n     Credit Union Administration, transmitting the \n     Administration's final rule -- Civil Monetary Penalty \n     Inflation Adjustment (RIN: 3133-AF09) received February 3, \n     2020, pursuant to 5 U.S.C. 801(a)(1)(A); Public Law 104-121, \n     Sec. 251; (110 Stat. 868); to the Committee on the Judiciary.\n       3734. A letter from the Chairman, Office of Proceedings, \n     Surface Transportation Board, transmitting the Board's final \n     rule -- Civil Monetary Penalties--2020 Adjustment [Docket \n     No.: EP 716 (Sub-No. 50)] received February 3, 2020, pursuant \n     to 5 U.S.C. 801(a)(1)(A); Public Law 104-121, Sec. 251; (110 \n     Stat. 868); to the Committee on the Judiciary.\n       3735. A letter from the Administrator, FEMA, Department of \n     Homeland Security, transmitting a report advising that the \n     cost of response and recovery efforts for FEMA-3426-EM in the \n     Commonwealth of Puerto Rico has exceeded the limit for a \n     single emergency declaration, pursuant to 42 U.S.C. \n     5193(b)(3); Public Law 93-288, Sec. 503(b)(3) (as amended by \n     Public Law 100-707, Sec. 107(a)); (102 Stat. 4707); to the \n     Committee on Transportation and Infrastructure.\n       3736. A letter from the Assistant Secretary of the Army \n     (Civil Works), Department of the Army, Department of Defense, \n     transmitting the 2019 Biennial Report to Congress on the \n     Status of the Missouri River Bank Stabilization and \n     Navigation Fish and Wildlife Mitigation Project, KS, MO, IA, \n     NE, pursuant to Public Law 113-121, Sec. 4003(e); (128 Stat. \n     1313); to the Committee on Transportation and Infrastructure.\n       3737. A letter from the Assistant Secretary of the Army \n     (Civil Works), Department of the Army, Department of Defense, \n     transmitting the Department's Reservoir Sediment Report, \n     pursuant to Sec. 1146(f) of the Water Resources Development \n     Act of 2018; to the Committee on Transportation and \n     Infrastructure.\n       3738. A letter from the Executive Director, Office of \n     Congressional Workplace Rights, transmitting the Office's \n     Annual Report on Awards and Settlements for Calendar Year \n     2019 for Employing Offices of the House of Representatives \n     and the Annual Report on Awards and Settlements for Calendar \n     Year 2019 for Employing Offices of the Senate, and other \n     Employing Offices, pursuant to 2 U.S.C. 1381(l)(1)(A); Public \n     Law 104-1, title III, 301(l)(1)(A) (as added by \n     201(a)(1)(B)); (132 Stat. 5315); jointly to the Committees on \n     House Administration and Education and Labor.\n\n\n", "turn": -1, "itemno": 0}, {"kind": "linebreak", "speaker": "None", "text": "                          ____________________\n\n\n", "turn": -1, "speaker_bioguide": null, "itemno": 1}], "related_laws": [{"congress": "93", "isprivate": "false", "number": "198"}, {"congress": "93", "isprivate": "false", "number": "288"}, {"congress": "99", "isprivate": "false", "number": "410"}, {"congress": "100", "isprivate": "false", "number": "707"}, {"congress": "104", "isprivate": "false", "number": "1"}, {"congress": "104", "isprivate": "false", "number": "121"}, {"congress": "105", "isprivate": "false", "number": "277"}, {"congress": "111", "isprivate": "false", "number": "84"}, {"congress": "113", "isprivate": "false", "number": "121"}], "related_usc": [{"title": "2", "detail": "(l)(1)(A)", "number": "1381"}, {"title": "5", "detail": "(a)", "number": "3349"}, {"title": "5", "detail": "(a)(1)(A)", "number": "801"}, {"title": "42", "detail": "(b)(3)", "number": "5193"}, {"title": "52", "detail": "(b)", "number": "20307"}], "related_statute": [{"volume": "87", "pages": "814"}, {"volume": "102", "pages": "4707"}, {"volume": "110", "pages": "868"}, {"volume": "112", "pages": "2681-614"}, {"volume": "123", "pages": "2333"}, {"volume": "128", "pages": "1313"}, {"volume": "132", "pages": "5315"}], "id": "CREC-2020-02-05-pt1-PgH845-3", "doc_title": "EXECUTIVE COMMUNICATIONS, ETC.", "title": "EXECUTIVE COMMUNICATIONS, ETC."}